Metadata-Version: 2.1
Name: fig-23dec
Version: 0.0
Summary: circle, tiangle, square
Author-email: daraaleksandrovic49627@gmail.com
